odoo9_addon_contract_show_invoice-9.0.1.2.0-py2.7-nspkg.pth
odoo9_addon_contract_show_invoice-9.0.1.2.0.dist-info/DESCRIPTION.rst
odoo9_addon_contract_show_invoice-9.0.1.2.0.dist-info/METADATA
odoo9_addon_contract_show_invoice-9.0.1.2.0.dist-info/RECORD
odoo9_addon_contract_show_invoice-9.0.1.2.0.dist-info/WHEEL
odoo9_addon_contract_show_invoice-9.0.1.2.0.dist-info/metadata.json
odoo9_addon_contract_show_invoice-9.0.1.2.0.dist-info/namespace_packages.txt
odoo9_addon_contract_show_invoice-9.0.1.2.0.dist-info/top_level.txt
odoo_addons/contract_show_invoice/README.rst
odoo_addons/contract_show_invoice/__init__.py
odoo_addons/contract_show_invoice/__openerp__.py
odoo_addons/contract_show_invoice/i18n/ar.po
odoo_addons/contract_show_invoice/i18n/bg.po
odoo_addons/contract_show_invoice/i18n/bs.po
odoo_addons/contract_show_invoice/i18n/ca.po
odoo_addons/contract_show_invoice/i18n/cs.po
odoo_addons/contract_show_invoice/i18n/de.po
odoo_addons/contract_show_invoice/i18n/el_GR.po
odoo_addons/contract_show_invoice/i18n/en_GB.po
odoo_addons/contract_show_invoice/i18n/es.po
odoo_addons/contract_show_invoice/i18n/es_CR.po
odoo_addons/contract_show_invoice/i18n/es_EC.po
odoo_addons/contract_show_invoice/i18n/es_MX.po
odoo_addons/contract_show_invoice/i18n/et.po
odoo_addons/contract_show_invoice/i18n/fi.po
odoo_addons/contract_show_invoice/i18n/fr.po
odoo_addons/contract_show_invoice/i18n/fr_CA.po
odoo_addons/contract_show_invoice/i18n/fr_CH.po
odoo_addons/contract_show_invoice/i18n/gl.po
odoo_addons/contract_show_invoice/i18n/hr.po
odoo_addons/contract_show_invoice/i18n/hr_HR.po
odoo_addons/contract_show_invoice/i18n/hu.po
odoo_addons/contract_show_invoice/i18n/id.po
odoo_addons/contract_show_invoice/i18n/it.po
odoo_addons/contract_show_invoice/i18n/ja.po
odoo_addons/contract_show_invoice/i18n/lt.po
odoo_addons/contract_show_invoice/i18n/mk.po
odoo_addons/contract_show_invoice/i18n/mn.po
odoo_addons/contract_show_invoice/i18n/nb.po
odoo_addons/contract_show_invoice/i18n/nb_NO.po
odoo_addons/contract_show_invoice/i18n/nl.po
odoo_addons/contract_show_invoice/i18n/nl_BE.po
odoo_addons/contract_show_invoice/i18n/pl.po
odoo_addons/contract_show_invoice/i18n/pt.po
odoo_addons/contract_show_invoice/i18n/pt_BR.po
odoo_addons/contract_show_invoice/i18n/pt_PT.po
odoo_addons/contract_show_invoice/i18n/ro.po
odoo_addons/contract_show_invoice/i18n/ru.po
odoo_addons/contract_show_invoice/i18n/sk_SK.po
