Metadata-Version: 2.0
Name: odoo9-addon-contract-show-invoice
Version: 9.0.1.2.0
Summary: Button in contracts to show their invoices
Home-page: http://www.domatix.com
Author: Domatix,Tecnativa,Odoo Community Association (OCA)
Author-email: support@odoo-community.org
License: UNKNOWN
Platform: UNKNOWN
Classifier: Programming Language :: Python :: 2.7
Classifier: Framework :: Odoo
Requires-Dist: odoo (<9.1a,>=9.0a)
